etc/neutron/plugins/ml2/ml2_conf_arista.ini
networking_arista/__init__.py
networking_arista/_i18n.py
networking_arista/common/__init__.py
networking_arista/common/api.py
networking_arista/common/config.py
networking_arista/common/constants.py
networking_arista/common/db_lib.py
networking_arista/common/exceptions.py
networking_arista/common/utils.py
networking_arista/db/README
networking_arista/db/__init__.py
networking_arista/db/migration/README
networking_arista/db/migration/__init__.py
networking_arista/db/migration/alembic_migrations/README
networking_arista/db/migration/alembic_migrations/__init__.py
networking_arista/db/migration/alembic_migrations/env.py
networking_arista/db/migration/alembic_migrations/script.py.mako
networking_arista/db/migration/alembic_migrations/versions/296b4e0236e0_initial_db_version.py
networking_arista/db/migration/alembic_migrations/versions/CONTRACT_HEAD
networking_arista/db/migration/alembic_migrations/versions/EXPAND_HEAD
networking_arista/db/migration/alembic_migrations/versions/__init__.py
networking_arista/db/migration/alembic_migrations/versions/liberty/contract/47036dc8697a_initial_db_version_contract.py
networking_arista/db/migration/alembic_migrations/versions/liberty/expand/1c6993ce7db0_initial_db_version_expand.py
networking_arista/db/migration/alembic_migrations/versions/queens/contract/39c2eeb67116_drop_aristaprovisionednets.py
networking_arista/db/migration/alembic_migrations/versions/queens/contract/941bad5630c1_drop_aristaprovisionedvms.py
networking_arista/db/migration/alembic_migrations/versions/queens/contract/dc7bf9c1ab4d_drop_aristaprovisionedtenants.py
networking_arista/l3Plugin/__init__.py
networking_arista/l3Plugin/arista_l3_driver.py
networking_arista/l3Plugin/l3_arista.py
networking_arista/ml2/__init__.py
networking_arista/ml2/arista_resources.py
networking_arista/ml2/arista_sync.py
networking_arista/ml2/arista_trunk.py
networking_arista/ml2/mechanism_arista.py
networking_arista/ml2/rpc/__init__.py
networking_arista-2025.1.0.dist-info/AUTHORS
networking_arista-2025.1.0.dist-info/LICENSE
networking_arista-2025.1.0.dist-info/METADATA
networking_arista-2025.1.0.dist-info/WHEEL
networking_arista-2025.1.0.dist-info/entry_points.txt
networking_arista-2025.1.0.dist-info/pbr.json
networking_arista-2025.1.0.dist-info/top_level.txt
networking_arista-2025.1.0.dist-info/RECORD
