Metadata-Version: 2.1
Name: networking_arista
Version: 2025.1.0
Summary: Arista Networking drivers
Home-page: https://opendev.org/x/networking-arista/
Author: Arista Networks
Author-email: openstack-dev@arista.com
Classifier: Environment :: OpenStack
Classifier: Intended Audience :: Information Technology
Classifier: Intended Audience :: System Administrators
Classifier: License :: OSI Approved :: Apache Software License
Classifier: Operating System :: POSIX :: Linux
Classifier: Programming Language :: Python
Classifier: Programming Language :: Python :: 3
Classifier: Programming Language :: Python :: 3.9
Classifier: Programming Language :: Python :: 3.10
Classifier: Programming Language :: Python :: 3.11
Classifier: Programming Language :: Python :: 3.12
Requires-Python: >=3.9
License-File: LICENSE
License-File: AUTHORS
Requires-Dist: pbr >=4.0.0
Requires-Dist: alembic >=1.6.5
Requires-Dist: neutron-lib >=3.17.0
Requires-Dist: oslo.i18n >=3.20.0
Requires-Dist: oslo.config >=9.4.0
Requires-Dist: oslo.log >=5.3.0
Requires-Dist: oslo.service >=3.5.0
Requires-Dist: oslo.utils >=7.3.0
Requires-Dist: requests >=2.32.3
Requires-Dist: six >=1.10.0
Requires-Dist: SQLAlchemy >=1.4.23
